jaxscape/__init__.py
jaxscape/connectivity_analysis.py
jaxscape/distance.py
jaxscape/euclidean_distance.py
jaxscape/graph.py
jaxscape/landmarks.py
jaxscape/lcp_distance.py
jaxscape/resistance_distance.py
jaxscape/rsp_distance.py
jaxscape/utils.py
jaxscape/window_operation.py
jaxscape/windowed_analysis.py
jaxscape/solvers/__init__.py
jaxscape/solvers/cholmodsolver.py
jaxscape/solvers/operator.py
jaxscape/solvers/pyamgsolver.py
jaxscape-0.0.6.dist-info/METADATA
jaxscape-0.0.6.dist-info/WHEEL
jaxscape-0.0.6.dist-info/licenses/LICENSE
jaxscape-0.0.6.dist-info/RECORD
