Metadata-Version: 2.4
Name: jaxscape
Version: 0.0.6
Summary: A minimal JAX library for connectivity modelling at scale
Project-URL: Documentation, https://github.com/vboussange/jaxscape#readme
Project-URL: Issues, https://github.com/vboussange/jaxscape/issues
Project-URL: Source, https://github.com/vboussange/jaxscape
Author-email: Victor Boussange <vic.boussange@gmail.com>
License: MIT License
License-File: LICENSE
Keywords: graph,jax,machine-learning,network
Classifier: Development Status :: 3 - Alpha
Classifier: Intended Audience :: Developers
Classifier: Intended Audience :: Financial and Insurance Industry
Classifier: Intended Audience :: Information Technology
Classifier: Intended Audience :: Science/Research
Classifier: License :: OSI Approved :: MIT License
Classifier: Natural Language :: English
Classifier: Programming Language :: Python :: 3
Classifier: Topic :: Scientific/Engineering :: Artificial Intelligence
Classifier: Topic :: Scientific/Engineering :: Bio-Informatics
Classifier: Topic :: Scientific/Engineering :: GIS
Classifier: Topic :: Scientific/Engineering :: Information Analysis
Classifier: Topic :: Scientific/Engineering :: Mathematics
Requires-Python: <3.13,>=3.10
Requires-Dist: equinox>=0.13.2
Requires-Dist: jax!=0.7.0,!=0.7.1,>=0.4.38
Requires-Dist: lineax>=0.0.8
Requires-Dist: numpy
Requires-Dist: tqdm>=4.66.1
Provides-Extra: cholespy
Requires-Dist: cholespy>=2.1.0; extra == 'cholespy'
Provides-Extra: dev
Requires-Dist: ipykernel>=6.29.5; extra == 'dev'
Provides-Extra: docs
Requires-Dist: mkdocs-include-exclude-files==0.1.0; extra == 'docs'
Requires-Dist: mkdocs-ipynb==0.1.1; extra == 'docs'
Requires-Dist: mkdocs-material>=9.5.0; extra == 'docs'
Requires-Dist: mkdocs>=1.5.0; extra == 'docs'
Requires-Dist: mkdocstrings[python]>=0.24.0; extra == 'docs'
Requires-Dist: pymdown-extensions>=10.7.0; extra == 'docs'
Provides-Extra: examples
Requires-Dist: flax; extra == 'examples'
Requires-Dist: geopandas; extra == 'examples'
Requires-Dist: matplotlib; extra == 'examples'
Requires-Dist: optimistix; extra == 'examples'
Requires-Dist: rioxarray; extra == 'examples'
Requires-Dist: scikit-learn; extra == 'examples'
Provides-Extra: pyamg
Requires-Dist: pyamg>=5.1.0; extra == 'pyamg'
Provides-Extra: solvers
Requires-Dist: cholespy>=2.1.0; extra == 'solvers'
Requires-Dist: pyamg<5.3.0,>=5.1.0; extra == 'solvers'
Provides-Extra: tests
Requires-Dist: networkx>=3.4; extra == 'tests'
Requires-Dist: pytest>=8.3.5; extra == 'tests'
